phsp_cmb/builder.py
phsp_cmb/phsp.py
phsp_cmb/phsp_cmb.py
rx_phsp_cmb-0.0.3.dist-info/METADATA
rx_phsp_cmb-0.0.3.dist-info/WHEEL
rx_phsp_cmb-0.0.3.dist-info/top_level.txt
rx_phsp_cmb-0.0.3.dist-info/RECORD
